Program 9/rshift.v
module rshift(input clk,input clrb,input sdr,output reg [3:0]q);
always @(posedge(clk),negedge(clrb))
if(~clrb)
q<=4'b0000;
else
q<={sdr,q[3:1]};
endmodule

Program 9/test_rshift.v
`include "rshift.v"
module test_rshift;
reg clk,clrb,sdr;
wire [3:0]q;
rshift rs(clk,clrb,sdr,q);
initial
begin
$dumpfile("shift.vcd");
$dumpvars(0,test_rshift);
clk=1;
clrb=0;
sdr=1;
#100
clrb=1;
sdr=1;
#150
sdr=0;
#200
$finish;
end
always #5 clk=~clk;
endmodule

Program 9/shift.vcd
$date
	Fri Dec 18 15:34:07 2020
$end
$version
	Icarus Verilog
$end
$timescale
	1s
$end
$scope module test_rshift $end
$var wire 4 ! q [3:0] $end
$var reg 1 " clk $end
$var reg 1 # clrb $end
$var reg 1 $ sdr $end
$scope module rs $end
$var wire 1 " clk $end
$var wire 1 # clrb $end
$var wire 1 $ sdr $end
$var reg 4 % q [3:0] $end
$upscope $end
$upscope $end
$enddefinitions $end
#0
$dumpvars
b0 %
1$
0#
1"
b0 !
$end
#5
0"
#10
1"
#15
0"
#20
1"
#25
0"
#30
1"
#35
0"
#40
1"
#45
0"
#50
1"
#55
0"
#60
1"
#65
0"
#70
1"
#75
0"
#80
1"
#85
0"
#90
1"
#95
0"
#100
b1000 !
b1000 %
1"
1#
#105
0"
#110
b1100 !
b1100 %
1"
#115
0"
#120
b1110 !
b1110 %
1"
#125
0"
#130
b1111 !
b1111 %
1"
#135
0"
#140
1"
#145
0"
#150
1"
#155
0"
#160
1"
#165
0"
#170
1"
#175
0"
#180
1"
#185
0"
#190
1"
#195
0"
#200
1"
#205
0"
#210
1"
#215
0"
#220
1"
#225
0"
#230
1"
#235
0"
#240
1"
#245
0"
#250
b111 !
b111 %
1"
0$
#255
0"
#260
b11 !
b11 %
1"
#265
0"
#270
b1 !
b1 %
1"
#275
0"
#280
b0 !
b0 %
1"
