Program 4/mux4to1.v
module mux4to1(a, b, c, d, sel1, sel2, y);
input a, b, c, d, sel1, sel2;
output y;
wire and1, and2, and3, and4;
and g1(and1, a, ~sel1, ~sel2);
and g2(and2, b, ~sel1, sel2);
and g3(and3, c, sel1, ~sel2);
and g4(and4, d, sel1, sel2);
or g5(y, and1, and2, and3, and4);
endmodule

Program 4/testmux4to1.v
module test;
reg a, b, c, d, sel1, sel2;
wire y;
mux4to1 mg(a, b, c, d, sel1, sel2, y);
initial
begin
 $dumpfile("mux4to1.vcd");
$dumpvars(0, test);
a = 0; b = 0; c = 0; d = 0; sel1 = 0; sel2 = 0;
#20
a = 1; b = 0; c = 0; d = 0; sel1 = 0; sel2 = 0;
#20
a = 0; b = 0; c = 0; d = 0; sel1 = 0; sel2 = 1;
#20
a = 0; b = 1; c = 0; d = 0; sel1 = 0; sel2 = 1;
#20
a = 0; b = 0; c = 0; d = 0; sel1 = 1; sel2 = 0;
#20
a = 0; b = 0; c = 1; d = 0; sel1 = 1; sel2 = 0;
#20
a = 0; b = 0; c = 0; d = 0; sel1 = 1; sel2 = 1;
#20
a = 0; b = 0; c = 0; d = 1; sel1 = 1; sel2 = 1;
#20
$finish;
end
endmodule

Program 4/mux4to1.vcd
$date
	Fri Dec 18 19:39:47 2020
$end
$version
	Icarus Verilog
$end
$timescale
	1s
$end
$scope module test $end
$var wire 1 ! y $end
$var reg 1 " a $end
$var reg 1 # b $end
$var reg 1 $ c $end
$var reg 1 % d $end
$var reg 1 & sel1 $end
$var reg 1 ' sel2 $end
$scope module mg $end
$var wire 1 " a $end
$var wire 1 ( and1 $end
$var wire 1 ) and2 $end
$var wire 1 * and3 $end
$var wire 1 + and4 $end
$var wire 1 # b $end
$var wire 1 $ c $end
$var wire 1 % d $end
$var wire 1 & sel1 $end
$var wire 1 ' sel2 $end
$var wire 1 ! y $end
$upscope $end
$upscope $end
$enddefinitions $end
#0
$dumpvars
0+
0*
0)
0(
0'
0&
0%
0$
0#
0"
0!
$end
#20
1!
1(
1"
#40
0!
0(
1'
0"
#60
1!
1)
1#
#80
0!
0)
0'
1&
0#
#100
1!
1*
1$
#120
0!
0*
1'
0$
#140
1!
1+
1%
